scriptpak/__main__.py
scriptpak-0.3.dist-info/METADATA
scriptpak-0.3.dist-info/WHEEL
scriptpak-0.3.dist-info/top_level.txt
scriptpak-0.3.dist-info/RECORD
